MANIFEST.in
README.md
requirements.txt
setup.py
Loanapp/VERSION
Loanapp/__init__.py
Loanapp/pipeline.py
Loanapp/predict.py
Loanapp/training_pipeline.py
Loanapp.egg-info/PKG-INFO
Loanapp.egg-info/SOURCES.txt
Loanapp.egg-info/dependency_links.txt
Loanapp.egg-info/requires.txt
Loanapp.egg-info/top_level.txt
Loanapp/config/__init__.py
Loanapp/config/config.py
Loanapp/datasets/loanTrain.csv
Loanapp/datasets/test_loan.csv
Loanapp/processing/__init__.py
Loanapp/processing/data_handling.py
Loanapp/processing/data_preprocessing.py
Loanapp/trained_models/classification.pkl
tests/test_predictions.py